<archimate:ArchimateDiagramModel
    xmlns:xsi="http://www.w3.org/2001/XMLSchema-instance"
    xmlns:archimate="http://www.archimatetool.com/archimate"
    name="LeanUX Reduce Costs (BlueSea)"
    id="id-816e86fbdc8c4c36a409bfc4151e5d04"
    documentation="page 10 Blue Sea Delivrables.pdf&#xA;Additional page 21f business scenario &#xA;&#xA;Business Scenario&#xA;Problem Statement&#xA;Newly merged organisation needs to modernise and evolve in order to compete at the top level.&#xA;Actors and Systems&#xA; Fish Suppliers&#xA; Fish Processors&#xA; Fish Resellers (Supermarkets)&#xA; Regulatory Bodies&#xA; Blue Sea centralised system&#xA;Business and Technical Environment&#xA;Fish is an essential international business providing fish. Technical environment uses all the modern technologies, including Cell Phones and Internet.&#xA;Business Outcomes&#xA;To increase revenue, especially to supermarkets. To reduce costs.">
  <children
      xsi:type="archimate:DiagramModelNote"
      id="id-6a2d0f07b6594c84994e224b24d4d970"
      font="1|arial|10.0|0|WINDOWS|1|0|0|0|0|0|0|0|0|1|0|0|0|0|arial"
      fontColor="#000000"
      lineColor="#000000"
      textAlignment="1"
      fillColor="#ffffff"
      content="Source: https://jeffgothelf.com/blog/leanuxcanvas-v2/ Creative Commons (CC BY-SA 4.0)">
    <bounds
        x="24"
        y="516"
        width="429"
        height="20"/>
  </children>
  <children
      xsi:type="archimate:DiagramModelNote"
      id="id-3c7fd619b3ad4932bfbe853bc69fa642"
      font="1|arial|10.0|0|WINDOWS|1|0|0|0|0|0|0|0|0|1|0|0|0|0|arial"
      fontColor="#000000"
      lineColor="#000000"
      textAlignment="1"
      fillColor="#ffffff"
      content="Title of initiative: Reduce Costs">
    <bounds
        x="452"
        y="33"
        width="373"
        height="20"/>
  </children>
  <children
      xsi:type="archimate:DiagramModelNote"
      id="id-91c7fe6e7d874b39a7e0d5f355125997"
      font="1|Arial|18.0|0|COCOA|1|ArialMT"
      lineColor="#000000"
      textAlignment="1"
      fillColor="#ffffff"
      content="Lean UX Canvas (v2)">
    <bounds
        x="24"
        y="24"
        width="334"
        height="37"/>
  </children>
  <children
      xsi:type="archimate:DiagramModelArchimateObject"
      id="id-3a3b8a929d7549c6b51bffa80adf7cab"
      targetConnections="id-617944d26e804408bd5aa78b67ba0a71"
      textAlignment="1">
    <bounds
        x="24"
        y="72"
        width="400"
        height="140"/>
    <children
        xsi:type="archimate:DiagramModelNote"
        id="id-d5c0d04e524841888f6beed0f90903a0"
        textAlignment="1">
      <features
          name="labelExpression"
          value="$connection:target{documentation}"/>
      <sourceConnections
          id="id-617944d26e804408bd5aa78b67ba0a71"
          source="id-d5c0d04e524841888f6beed0f90903a0"
          target="id-3a3b8a929d7549c6b51bffa80adf7cab"/>
      <bounds
          y="24"
          width="397"
          height="49"/>
    </children>
    <children
        xsi:type="archimate:DiagramModelArchimateObject"
        id="id-6b8a743b78c6454fa9b41ff9b22a2117">
      <bounds
          x="276"
          y="76"
          width="95"
          height="25"/>
      <archimateElement
          xsi:type="archimate:BusinessFunction"
          href="BusinessFunction_id-2dfca765cb2f41348c01284d7238df35.xml#id-2dfca765cb2f41348c01284d7238df35"/>
    </children>
    <children
        xsi:type="archimate:DiagramModelArchimateObject"
        id="id-e6d456139e3241379bbecf4b59a7e814">
      <bounds
          x="168"
          y="76"
          width="95"
          height="25"/>
      <archimateElement
          xsi:type="archimate:BusinessFunction"
          href="BusinessFunction_id-ee5a42fc14e441a69beb9f0f88f6050e.xml#id-ee5a42fc14e441a69beb9f0f88f6050e"/>
    </children>
    <children
        xsi:type="archimate:DiagramModelArchimateObject"
        id="id-37c5f4a53bc841d2999fae114d7914f3">
      <bounds
          x="216"
          y="108"
          width="95"
          height="25"/>
      <archimateElement
          xsi:type="archimate:BusinessFunction"
          href="BusinessFunction_id-cac49483ae154947aa57e109a4f7a206.xml#id-cac49483ae154947aa57e109a4f7a206"/>
    </children>
    <children
        xsi:type="archimate:DiagramModelArchimateObject"
        id="id-37c7675a0f4d43699333dad50b745c2a">
      <bounds
          x="24"
          y="72"
          width="120"
          height="33"/>
      <archimateElement
          xsi:type="archimate:Driver"
          href="Driver_id-37ef918cb29e4ab788c0282a188cd605.xml#id-37ef918cb29e4ab788c0282a188cd605"/>
    </children>
    <archimateElement
        xsi:type="archimate:Grouping"
        href="Grouping_id-bc902afb9ac0459b8678259b46cca44f.xml#id-bc902afb9ac0459b8678259b46cca44f"/>
  </children>
  <children
      xsi:type="archimate:DiagramModelArchimateObject"
      id="id-424426bfe0e14d5bb16bfc7f9642b48c"
      targetConnections="id-da02679272bb4b10b1e3a36cab5f727f"
      textAlignment="1">
    <bounds
        x="692"
        y="72"
        width="400"
        height="140"/>
    <children
        xsi:type="archimate:DiagramModelNote"
        id="id-809487aaa73f45a3a37a3a5e70c7d8ea"
        textAlignment="1">
      <features
          name="labelExpression"
          value="$connection:target{documentation}"/>
      <sourceConnections
          id="id-da02679272bb4b10b1e3a36cab5f727f"
          source="id-809487aaa73f45a3a37a3a5e70c7d8ea"
          target="id-424426bfe0e14d5bb16bfc7f9642b48c"/>
      <bounds
          y="24"
          width="397"
          height="49"/>
    </children>
    <children
        xsi:type="archimate:DiagramModelArchimateObject"
        id="id-d12a774110704c90a5c6f42c3eb101a5">
      <bounds
          x="156"
          y="72"
          width="120"
          height="55"/>
      <archimateElement
          xsi:type="archimate:Goal"
          href="Goal_id-dffc45bfa4174f92a78b67263e8e36c8.xml#id-dffc45bfa4174f92a78b67263e8e36c8"/>
    </children>
    <archimateElement
        xsi:type="archimate:Grouping"
        href="Grouping_id-08ef0dd86ead4d4cab7f5e2d46025bc6.xml#id-08ef0dd86ead4d4cab7f5e2d46025bc6"/>
  </children>
  <children
      xsi:type="archimate:DiagramModelArchimateObject"
      id="id-e5d33ea7be824c0cb6ac43b69bb3d928"
      targetConnections="id-3ea624d0151b439f8d48362fbb99fe8c"
      textAlignment="1">
    <bounds
        x="24"
        y="216"
        width="400"
        height="140"/>
    <children
        xsi:type="archimate:DiagramModelNote"
        id="id-8a32c908407e4e7498ceb0c9a778805d"
        textAlignment="1">
      <features
          name="labelExpression"
          value="$connection:target{documentation}"/>
      <sourceConnections
          id="id-3ea624d0151b439f8d48362fbb99fe8c"
          source="id-8a32c908407e4e7498ceb0c9a778805d"
          target="id-e5d33ea7be824c0cb6ac43b69bb3d928"/>
      <bounds
          y="24"
          width="397"
          height="37"/>
    </children>
    <children
        xsi:type="archimate:DiagramModelArchimateObject"
        id="id-16e6f988cdb64d2abdba65c99f6a3e22">
      <bounds
          x="288"
          y="60"
          width="95"
          height="37"/>
      <archimateElement
          xsi:type="archimate:BusinessActor"
          href="BusinessActor_id-7384b33eaa8347e1923692b701bdb6dc.xml#id-7384b33eaa8347e1923692b701bdb6dc"/>
    </children>
    <children
        xsi:type="archimate:DiagramModelArchimateObject"
        id="id-0ac717daca4e448da8056b1f43b75c98">
      <bounds
          x="168"
          y="60"
          width="95"
          height="37"/>
      <archimateElement
          xsi:type="archimate:BusinessRole"
          href="BusinessRole_id-90403a4244db41f397f5e0317f25a471.xml#id-90403a4244db41f397f5e0317f25a471"/>
    </children>
    <children
        xsi:type="archimate:DiagramModelArchimateObject"
        id="id-760ad8ed1df74c49ba15007171027ee8">
      <bounds
          x="60"
          y="60"
          width="95"
          height="37"/>
      <archimateElement
          xsi:type="archimate:BusinessRole"
          href="BusinessRole_id-788c6942104248e78fa91ad0ff786c7a.xml#id-788c6942104248e78fa91ad0ff786c7a"/>
    </children>
    <children
        xsi:type="archimate:DiagramModelArchimateObject"
        id="id-6c8073476e9848da96590976dab3d35b">
      <bounds
          x="60"
          y="96"
          width="95"
          height="37"/>
      <archimateElement
          xsi:type="archimate:BusinessRole"
          href="BusinessRole_id-d4780de1f5f74d94a8973cc1d736ede2.xml#id-d4780de1f5f74d94a8973cc1d736ede2"/>
    </children>
    <children
        xsi:type="archimate:DiagramModelArchimateObject"
        id="id-97a2bc5bbcda404b82864b6a80d45afe">
      <bounds
          x="168"
          y="96"
          width="95"
          height="37"/>
      <archimateElement
          xsi:type="archimate:BusinessRole"
          href="BusinessRole_id-9a850987fc90439193edb3afa40fa644.xml#id-9a850987fc90439193edb3afa40fa644"/>
    </children>
    <children
        xsi:type="archimate:DiagramModelArchimateObject"
        id="id-644fa648a52d446087025b2e621eaeb7">
      <bounds
          x="288"
          y="96"
          width="95"
          height="37"/>
      <archimateElement
          xsi:type="archimate:BusinessRole"
          href="BusinessRole_id-210a0b3c485741c3b2964710280f38a7.xml#id-210a0b3c485741c3b2964710280f38a7"/>
    </children>
    <archimateElement
        xsi:type="archimate:Grouping"
        href="Grouping_id-46e8f2b378ee484b9040755069fc5958.xml#id-46e8f2b378ee484b9040755069fc5958"/>
  </children>
  <children
      xsi:type="archimate:DiagramModelArchimateObject"
      id="id-8ac6ed7076ea46e1a50b0c82729fe018"
      targetConnections="id-7ff27e1e8a6b4c23adff296f78022cb6"
      textAlignment="1">
    <bounds
        x="692"
        y="216"
        width="400"
        height="140"/>
    <children
        xsi:type="archimate:DiagramModelNote"
        id="id-326d835302544beca15976a8d8628724"
        textAlignment="1">
      <features
          name="labelExpression"
          value="$connection:target{documentation}"/>
      <sourceConnections
          id="id-7ff27e1e8a6b4c23adff296f78022cb6"
          source="id-326d835302544beca15976a8d8628724"
          target="id-8ac6ed7076ea46e1a50b0c82729fe018"/>
      <bounds
          y="24"
          width="397"
          height="49"/>
    </children>
    <children
        xsi:type="archimate:DiagramModelArchimateObject"
        id="id-8df77aaba5f242c9b6f44ba13c158891">
      <bounds
          x="139"
          y="72"
          width="120"
          height="25"/>
      <archimateElement
          xsi:type="archimate:Value"
          href="Value_id-f5424701e5744d579294c576409ad38e.xml#id-f5424701e5744d579294c576409ad38e"/>
    </children>
    <children
        xsi:type="archimate:DiagramModelArchimateObject"
        id="id-254c3483fa39428d894bae1a6c7759ff">
      <bounds
          x="264"
          y="72"
          width="120"
          height="25"/>
      <archimateElement
          xsi:type="archimate:Value"
          href="Value_id-0942f9f8c25e4a3daf7897fa5a082ce4.xml#id-0942f9f8c25e4a3daf7897fa5a082ce4"/>
    </children>
    <children
        xsi:type="archimate:DiagramModelArchimateObject"
        id="id-fbc38e34da7246f1bf1828cd269d73ad">
      <bounds
          x="24"
          y="72"
          width="95"
          height="25"/>
      <archimateElement
          xsi:type="archimate:BusinessRole"
          href="BusinessRole_id-825036d8e86e4292aeee162b431a5026.xml#id-825036d8e86e4292aeee162b431a5026"/>
    </children>
    <archimateElement
        xsi:type="archimate:Grouping"
        href="Grouping_id-f1036cded5c34a67a8d32e4148f3f1b9.xml#id-f1036cded5c34a67a8d32e4148f3f1b9"/>
  </children>
  <children
      xsi:type="archimate:DiagramModelArchimateObject"
      id="id-bc1b745940d4434480c1a90784150d6a"
      targetConnections="id-dde5a8262a63438883314d0cbd284780"
      textAlignment="1">
    <bounds
        x="24"
        y="360"
        width="400"
        height="140"/>
    <children
        xsi:type="archimate:DiagramModelNote"
        id="id-f963dbb7b269467386d29ed225295363"
        textAlignment="1">
      <features
          name="labelExpression"
          value="$connection:target{documentation}"/>
      <sourceConnections
          id="id-dde5a8262a63438883314d0cbd284780"
          source="id-f963dbb7b269467386d29ed225295363"
          target="id-bc1b745940d4434480c1a90784150d6a"/>
      <bounds
          y="24"
          width="397"
          height="49"/>
    </children>
    <children
        xsi:type="archimate:DiagramModelArchimateObject"
        id="id-018e9504ee314e0898398e30d400ffd6">
      <bounds
          x="24"
          y="72"
          width="120"
          height="55"/>
      <archimateElement
          xsi:type="archimate:Requirement"
          href="Requirement_id-d48a60e8aa1d411f9bc96c5464144ccd.xml#id-d48a60e8aa1d411f9bc96c5464144ccd"/>
    </children>
    <children
        xsi:type="archimate:DiagramModelArchimateObject"
        id="id-ece301d44e3d4ae6826da7d6720992d5">
      <bounds
          x="149"
          y="72"
          width="133"
          height="55"/>
      <archimateElement
          xsi:type="archimate:Requirement"
          href="Requirement_id-57b4383e4ff24487ad0255b001491421.xml#id-57b4383e4ff24487ad0255b001491421"/>
    </children>
    <archimateElement
        xsi:type="archimate:Grouping"
        href="Grouping_id-28632ea677a843aeb6de326b520a0e04.xml#id-28632ea677a843aeb6de326b520a0e04"/>
  </children>
  <children
      xsi:type="archimate:DiagramModelArchimateObject"
      id="id-c4fd33f5a4274df29c81efadd9ef56d2"
      targetConnections="id-750d69865d5443df9cd7e5a82915b91c"
      textAlignment="1">
    <bounds
        x="692"
        y="360"
        width="400"
        height="140"/>
    <children
        xsi:type="archimate:DiagramModelNote"
        id="id-fbd3ad8174584a6586dbc5eddd13faf6"
        textAlignment="1">
      <features
          name="labelExpression"
          value="$connection:target{documentation}"/>
      <sourceConnections
          id="id-750d69865d5443df9cd7e5a82915b91c"
          source="id-fbd3ad8174584a6586dbc5eddd13faf6"
          target="id-c4fd33f5a4274df29c81efadd9ef56d2"/>
      <bounds
          y="24"
          width="397"
          height="25"/>
    </children>
    <archimateElement
        xsi:type="archimate:Grouping"
        href="Grouping_id-dcb37d922e3d4802b3243906cdd3cfd1.xml#id-dcb37d922e3d4802b3243906cdd3cfd1"/>
  </children>
  <children
      xsi:type="archimate:DiagramModelArchimateObject"
      id="id-ee542cf916844a56a0d1ad037b098ae3"
      targetConnections="id-6a4c8ad3dca34790b42bc066a8a45a93"
      textAlignment="1">
    <bounds
        x="428"
        y="72"
        width="265"
        height="241"/>
    <children
        xsi:type="archimate:DiagramModelNote"
        id="id-bb525e040516485e8d1f1c4438a51f0e"
        textAlignment="1">
      <features
          name="labelExpression"
          value="$connection:target{documentation}"/>
      <sourceConnections
          id="id-6a4c8ad3dca34790b42bc066a8a45a93"
          source="id-bb525e040516485e8d1f1c4438a51f0e"
          target="id-ee542cf916844a56a0d1ad037b098ae3"/>
      <bounds
          y="24"
          width="253"
          height="49"/>
    </children>
    <children
        xsi:type="archimate:DiagramModelArchimateObject"
        id="id-abc2a5d94ef442d498ae706d3c80a049">
      <bounds
          x="12"
          y="84"
          width="120"
          height="55"/>
      <archimateElement
          xsi:type="archimate:Product"
          href="Product_id-73d0550e5420438b82db87f4cceca2fb.xml#id-73d0550e5420438b82db87f4cceca2fb"/>
    </children>
    <children
        xsi:type="archimate:DiagramModelArchimateObject"
        id="id-14ebaa046dc6405f9364da56e7886db7">
      <bounds
          x="133"
          y="84"
          width="120"
          height="55"/>
      <archimateElement
          xsi:type="archimate:Product"
          href="Product_id-2f7b8ac89dc7403a8a3cfbef3db5ce78.xml#id-2f7b8ac89dc7403a8a3cfbef3db5ce78"/>
    </children>
    <children
        xsi:type="archimate:DiagramModelArchimateObject"
        id="id-40544522ae4d4b5ea1484833ca67eaa3">
      <bounds
          x="133"
          y="144"
          width="120"
          height="25"/>
      <archimateElement
          xsi:type="archimate:BusinessCollaboration"
          href="BusinessCollaboration_id-7162f9532d21491dab692da15c77e66c.xml#id-7162f9532d21491dab692da15c77e66c"/>
    </children>
    <children
        xsi:type="archimate:DiagramModelArchimateObject"
        id="id-0ed70ccd729b45f9a72bb4d0c09eee7e">
      <bounds
          x="12"
          y="144"
          width="120"
          height="36"/>
      <archimateElement
          xsi:type="archimate:Outcome"
          href="Outcome_id-c8ee53230bbd4ce283d264dcb58ff8c7.xml#id-c8ee53230bbd4ce283d264dcb58ff8c7"/>
    </children>
    <archimateElement
        xsi:type="archimate:Grouping"
        href="Grouping_id-ce866e0df5214c38b871ab0a380bc5fd.xml#id-ce866e0df5214c38b871ab0a380bc5fd"/>
  </children>
  <children
      xsi:type="archimate:DiagramModelArchimateObject"
      id="id-76a2b7bdfa6240fe8384eeeb64f8133c"
      targetConnections="id-db7d44abbf9c4db396735be995e8fb46"
      textAlignment="1">
    <bounds
        x="428"
        y="312"
        width="265"
        height="188"/>
    <children
        xsi:type="archimate:DiagramModelNote"
        id="id-8f80627196e049c3ab51af1384a2eb54"
        textAlignment="1">
      <features
          name="labelExpression"
          value="$connection:target{documentation}"/>
      <sourceConnections
          id="id-db7d44abbf9c4db396735be995e8fb46"
          source="id-8f80627196e049c3ab51af1384a2eb54"
          target="id-76a2b7bdfa6240fe8384eeeb64f8133c"/>
      <bounds
          y="24"
          width="253"
          height="97"/>
    </children>
    <archimateElement
        xsi:type="archimate:Grouping"
        href="Grouping_id-9ce91b1bbda2402a87471c3393920e17.xml#id-9ce91b1bbda2402a87471c3393920e17"/>
  </children>
  <children
      xsi:type="archimate:DiagramModelNote"
      id="id-953f658aaef541f5bbaed325926b832c"
      font="1|arial|10.0|0|WINDOWS|1|0|0|0|0|0|0|0|0|1|0|0|0|0|arial"
      fontColor="#000000"
      lineColor="#000000"
      textAlignment="1"
      fillColor="#ffffff"
      content="Date:&#xA;Iteration:">
    <bounds
        x="884"
        y="24"
        width="208"
        height="37"/>
  </children>
</archimate:ArchimateDiagramModel>
